quizz/__init__.py
quizz-1.0.0.dist-info/LICENSE
quizz-1.0.0.dist-info/METADATA
quizz-1.0.0.dist-info/WHEEL
quizz-1.0.0.dist-info/top_level.txt
quizz-1.0.0.dist-info/RECORD
